{
  "qw" : 64,
  "qh" : 64,
  "box" : [
    { "x": 16, "y": 16, "w": 32, "h": 48, "bits": 0 }
  ],
  "frames" : [
    { "x": 0.000, "y": 0, "w": 0.125, "h": 0.125, "box": [ 0 ] },
    { "x": 0.125, "y": 0, "w": 0.125, "h": 0.125, "box": [ 0 ] },
    { "x": 0.250, "y": 0, "w": 0.125, "h": 0.125, "box": [ 0 ] },
    { "x": 0.375, "y": 0, "w": 0.125, "h": 0.125, "box": [ 0 ] },
    { "x": 0.500, "y": 0, "w": 0.125, "h": 0.125, "box": [ 0 ] },
    { "x": 0.625, "y": 0, "w": 0.125, "h": 0.125, "box": [ 0 ] },
    { "x": 0.750, "y": 0, "w": 0.125, "h": 0.125, "box": [ 0 ] },
    { "x": 0.875, "y": 0, "w": 0.125, "h": 0.125, "box": [ 0 ] },
    { "x": 0.375, "y": 0.375, "w": 0.125, "h": 0.125, "ox" : 0, "oy" : 8, "box": [ 0 ] }
  ],
  "animations" : [
    {
      "id" : 0, // Idle
      "loop" : 1,
      "interval" : 10,
      "frames" : [ 0, 0, 0, 0, 0, 0, 0, 1 ]
    },
    {
      "id" : 1, // Walk
      "loop" : 1,
      "interval" : 10,
      "frames" : [ 2, 3, 4, 3 ]
    },
    {
      "id" : 2, // Walk with gun
      "loop" : 1,
      "interval" : 10,
      "frames" : [ 5, 6, 7, 6 ]
    },
    {
      "id" : 3, // Jump
      "loop" : 1,
      "interval" : 10,
      "frames" : [ 8 ]
    }
  ]
}
